pyverbal/__init__.py
pyverbal/conjugation/__init__.py
pyverbal/conjugation/base.py
pyverbal/conjugation/langs.py
pyverbal/conjugation/ptbr.py
pyverbal/data/pt-Br/conjugation.yaml
pyverbal/lang/__init__.py
pyverbal/lang/ptbr.py
pyverbal-1.0.0.dist-info/LICENSE
pyverbal-1.0.0.dist-info/METADATA
pyverbal-1.0.0.dist-info/WHEEL
pyverbal-1.0.0.dist-info/top_level.txt
pyverbal-1.0.0.dist-info/RECORD
