Metadata-Version: 2.1
Name: pyverbal
Version: 1.0.0
Summary: Verbs conjugation and desconjugation
Home-page: https://github.com/metadeta96/pyverbal
Author: metadeta96
Author-email: metadeta96@gmail.com
License: UNKNOWN
Download-URL: https://github.com/metadeta96/pyverbal
Keywords: verbs,grammar,conjugation,pt-br,pt,portugues,portuguese,gramatica,verbal,conjugacao
Platform: UNKNOWN
Classifier: Programming Language :: Python :: 3
Classifier: License :: OSI Approved :: GNU Lesser General Public License v3 or later (LGPLv3+)
Classifier: Operating System :: OS Independent
Requires-Python: >=3.6
Requires-Dist: pyyaml
